[
    {
        "name": "Real Madrid",
        "url": "https:\/\/www.transfermarkt.es\/real-madrid\/spielplan\/verein\/418\/saison_id\/2024",
        "external_id": "418"
    },
    {
        "name": "FC Barcelona",
        "url": "https:\/\/www.transfermarkt.es\/fc-barcelona\/spielplan\/verein\/131\/saison_id\/2024",
        "external_id": "131"
    },
    {
        "name": "Atl\u00e9tico Madrid",
        "url": "https:\/\/www.transfermarkt.es\/atletico-madrid\/spielplan\/verein\/13\/saison_id\/2024",
        "external_id": "13"
    },
    {
        "name": "Real Sociedad",
        "url": "https:\/\/www.transfermarkt.es\/real-sociedad-san-sebastian\/spielplan\/verein\/681\/saison_id\/2024",
        "external_id": "681"
    },
    {
        "name": "Athletic",
        "url": "https:\/\/www.transfermarkt.es\/athletic-bilbao\/spielplan\/verein\/621\/saison_id\/2024",
        "external_id": "621"
    },
    {
        "name": "Villarreal CF",
        "url": "https:\/\/www.transfermarkt.es\/fc-villarreal\/spielplan\/verein\/1050\/saison_id\/2024",
        "external_id": "1050"
    },
    {
        "name": "Valencia CF",
        "url": "https:\/\/www.transfermarkt.es\/fc-valencia\/spielplan\/verein\/1049\/saison_id\/2024",
        "external_id": "1049"
    },
    {
        "name": "Girona FC",
        "url": "https:\/\/www.transfermarkt.es\/fc-girona\/spielplan\/verein\/12321\/saison_id\/2024",
        "external_id": "12321"
    },
    {
        "name": "Sevilla FC",
        "url": "https:\/\/www.transfermarkt.es\/fc-sevilla\/spielplan\/verein\/368\/saison_id\/2024",
        "external_id": "368"
    },
    {
        "name": "Real Betis",
        "url": "https:\/\/www.transfermarkt.es\/real-betis-sevilla\/spielplan\/verein\/150\/saison_id\/2024",
        "external_id": "150"
    },
    {
        "name": "UD Las Palmas",
        "url": "https:\/\/www.transfermarkt.es\/ud-las-palmas\/spielplan\/verein\/472\/saison_id\/2024",
        "external_id": "472"
    },
    {
        "name": "CA Osasuna",
        "url": "https:\/\/www.transfermarkt.es\/ca-osasuna\/spielplan\/verein\/331\/saison_id\/2024",
        "external_id": "331"
    },
    {
        "name": "RC Celta",
        "url": "https:\/\/www.transfermarkt.es\/celta-vigo\/spielplan\/verein\/940\/saison_id\/2024",
        "external_id": "940"
    },
    {
        "name": "RCD Espanyol",
        "url": "https:\/\/www.transfermarkt.es\/espanyol-barcelona\/spielplan\/verein\/714\/saison_id\/2024",
        "external_id": "714"
    },
    {
        "name": "RCD Mallorca",
        "url": "https:\/\/www.transfermarkt.es\/rcd-mallorca\/spielplan\/verein\/237\/saison_id\/2024",
        "external_id": "237"
    },
    {
        "name": "Getafe CF",
        "url": "https:\/\/www.transfermarkt.es\/fc-getafe\/spielplan\/verein\/3709\/saison_id\/2024",
        "external_id": "3709"
    },
    {
        "name": "Alav\u00e9s",
        "url": "https:\/\/www.transfermarkt.es\/deportivo-alaves\/spielplan\/verein\/1108\/saison_id\/2024",
        "external_id": "1108"
    },
    {
        "name": "Rayo Vallecano",
        "url": "https:\/\/www.transfermarkt.es\/rayo-vallecano\/spielplan\/verein\/367\/saison_id\/2024",
        "external_id": "367"
    },
    {
        "name": "Real Valladolid",
        "url": "https:\/\/www.transfermarkt.es\/real-valladolid\/spielplan\/verein\/366\/saison_id\/2024",
        "external_id": "366"
    },
    {
        "name": "CD Legan\u00e9s",
        "url": "https:\/\/www.transfermarkt.es\/cd-leganes\/spielplan\/verein\/1244\/saison_id\/2024",
        "external_id": "1244"
    }
]